LICENSE.txt
MANIFEST.in
setup.py
Django_tinymce_filebrowser.egg-info/PKG-INFO
Django_tinymce_filebrowser.egg-info/SOURCES.txt
Django_tinymce_filebrowser.egg-info/dependency_links.txt
Django_tinymce_filebrowser.egg-info/not-zip-safe
Django_tinymce_filebrowser.egg-info/requires.txt
Django_tinymce_filebrowser.egg-info/top_level.txt
mce_filebrowser/__init__.py
mce_filebrowser/admin.py
mce_filebrowser/forms.py
mce_filebrowser/models.py
mce_filebrowser/urls.py
mce_filebrowser/views.py
mce_filebrowser/static/mce_filebrowser/css/mce_filebrowser.css
mce_filebrowser/static/mce_filebrowser/js/filebrowser_init.js
mce_filebrowser/templates/filebrowser.html